README.rst
setup.py
django_xvalidate.egg-info/PKG-INFO
django_xvalidate.egg-info/SOURCES.txt
django_xvalidate.egg-info/dependency_links.txt
django_xvalidate.egg-info/requires.txt
django_xvalidate.egg-info/top_level.txt
xvalidate/__init__.py
xvalidate/models.py
xvalidate/validators.py