Metadata-Version: 1.1
Name: django-xvalidate
Version: 0.4.2
Summary: Cross-field validators within a Django model
Home-page: https://www.github.com/suriya/django-xvalidate
Author: Suriya Subramanian
Author-email: suriya@alumni.cs.utexas.edu
License: MIT License
Platform: UNKNOWN
Classifier: Environment :: Web Environment
Classifier: Framework :: Django
Classifier: Intended Audience :: Developers
Classifier: License :: OSI Approved :: MIT License
Classifier: Operating System :: OS Independent
Classifier: Programming Language :: Python
Classifier: Programming Language :: Python :: 2
Classifier: Programming Language :: Python :: 2.7
Classifier: Programming Language :: Python :: 3
Classifier: Programming Language :: Python :: 3.5
Classifier: Topic :: Internet :: WWW/HTTP
Classifier: Topic :: Internet :: WWW/HTTP :: Dynamic Content
